qiye_wechat_mcp/__init__.py
qiye_wechat_mcp/__main__.py
qiye_wechat_mcp/server.py
qiye_wechat_mcp-0.1.5.dist-info/licenses/LICENSE
tests/__init__.py
tests/test_server.py
qiye_wechat_mcp-0.1.5.dist-info/METADATA
qiye_wechat_mcp-0.1.5.dist-info/WHEEL
qiye_wechat_mcp-0.1.5.dist-info/entry_points.txt
qiye_wechat_mcp-0.1.5.dist-info/top_level.txt
qiye_wechat_mcp-0.1.5.dist-info/RECORD
